LICENSE.md
MANIFEST.in
README.md
setup.py
XAFSmass/XAFSmassCalc.py
XAFSmass/XAFSmassQt.py
XAFSmass/__init__.py
XAFSmass/materials_simple.py
XAFSmass/tests.py
XAFSmass.egg-info/PKG-INFO
XAFSmass.egg-info/SOURCES.txt
XAFSmass.egg-info/dependency_links.txt
XAFSmass.egg-info/not-zip-safe
XAFSmass.egg-info/requires.txt
XAFSmass.egg-info/top_level.txt
XAFSmass/data/AtomicData.dat
XAFSmass/data/BrCo.npz
XAFSmass/data/Chantler.npz
XAFSmass/data/Energies.txt
XAFSmass/data/Henke.npz
XAFSmass/help/genindex.html
XAFSmass/help/index.html
XAFSmass/help/license.html
XAFSmass/help/objects.inv
XAFSmass/help/py-modindex.html
XAFSmass/help/search.html
XAFSmass/help/searchindex.js
XAFSmass/help/_images/1powder_150.png
XAFSmass/help/_images/3gas_150.png
XAFSmass/help/_images/SNtransm050.png
XAFSmass/help/_images/SNtransm100.png
XAFSmass/help/_sources/index.rst.txt
XAFSmass/help/_sources/license.rst.txt
XAFSmass/help/_static/XAFSmassQt.ico
XAFSmass/help/_static/animation.js
XAFSmass/help/_static/basic.css
XAFSmass/help/_static/classic.css
XAFSmass/help/_static/default.css
XAFSmass/help/_static/doctools.js
XAFSmass/help/_static/documentation_options.js
XAFSmass/help/_static/file.png
XAFSmass/help/_static/language_data.js
XAFSmass/help/_static/minus.png
XAFSmass/help/_static/plus.png
XAFSmass/help/_static/pygments.css
XAFSmass/help/_static/searchtools.js
XAFSmass/help/_static/sidebar.js
XAFSmass/help/_static/sphinx_highlight.js
XAFSmass/help/_static/thumbnail.css