Metadata-Version: 2.2
Name: XAFSmass
Version: 1.7.0
Summary: A program for calculating the mass of XAFS samples. For synchrotron users.
Home-page: http://xafsmass.readthedocs.io
Author: Konstantin Klementiev, Roman Chernikov
Author-email: konstantin.klementiev@gmail.com, rchernikov@gmail.com
License: MIT License
Platform: OS Independent
Classifier: Development Status :: 5 - Production/Stable
Classifier: Intended Audience :: Science/Research
Classifier: Natural Language :: English
Classifier: Operating System :: OS Independent
Classifier: Programming Language :: Python :: 2
Classifier: Programming Language :: Python :: 3
Classifier: License :: OSI Approved :: MIT License
Classifier: Topic :: Scientific/Engineering :: Physics
Classifier: Topic :: Scientific/Engineering :: Visualization
License-File: LICENSE.md
Requires-Dist: numpy>=1.8.0
Requires-Dist: matplotlib>=2.0.0
Requires-Dist: distro
Requires-Dist: qtpy
Dynamic: author
Dynamic: author-email
Dynamic: classifier
Dynamic: description
Dynamic: description-content-type
Dynamic: home-page
Dynamic: keywords
Dynamic: license
Dynamic: platform
Dynamic: requires-dist
Dynamic: summary
